{
  "type": "rechiseled:chiseling",
  "overwrite": false,
  "entries": [
    {
      "item": "minecraft:crimson_planks"
    },
    {
      "item": "buildersdelight:crimson_planks_1"
    },
    {
      "item": "buildersdelight:crimson_planks_2"
    },
    {
      "item": "buildersdelight:crimson_planks_3"
    },
    {
      "item": "buildersdelight:crimson_planks_4"
    },
    {
      "item": "buildersdelight:crimson_planks_5"
    },
    {
      "item": "buildersdelight:crimson_planks_6"
    },
    {
      "item": "buildersdelight:crimson_planks_7"
    }
  ]
}